{
  "experiment_id": "M3_catboost_direct_history_metadata_engineered",
  "model_name": "CatBoostRegressor",
  "mode": "direct",
  "feature_set": "history_metadata_engineered",
  "baseline_reference": null,
  "timestamp_utc": "2026-06-09T13:13:38.886885+00:00",
  "catboost_params": {
    "loss_function": "RMSE",
    "iterations": 180,
    "learning_rate": 0.03,
    "depth": 4,
    "l2_leaf_reg": 8.0,
    "random_seed": 42,
    "od_type": "Iter",
    "od_wait": 20,
    "use_best_model": true
  },
  "best_iterations": [
    180,
    179,
    179,
    180,
    180,
    180,
    180,
    180,
    100
  ]
}